Workbook

Sheet Model Overview
A1: Model Overview
A3: 1. Company and Model Overview
A4: This model values a 5-year forecast for a hypothetical company with a starting revenue of $1,000,000. These forecasts include a Pro-Forma Income Statement, a Pro-Forma Balance Sheet, a Pro-Forma Cash Flow Statement, a Free Cash Flow Statement, a DCF Valuation, and the model's sensitivity analysis. The company uses a discounted cash flow valuation approach for determining its value.
A5: 2. Main Assumptions
A6: For this hypothetical company, the main assumptions are as follows; a revenue growth of 5%, costs of goods sold is 60% of the company's revenue, operating expenses are 20% of revenue, the tax rate is 25%, capital expenditures are 4% of revenue, the discount rate is 10%, and the company's terminal growth rate is 3%. These assumptions were recommended from the model's instructions. The model also addresses the following assumptions in addition to the recommended metrics from the instructions. This includes the company's starting revenue at $1,000,000, a fixed depreciation amount of $40,000 per year, a starting cash balance of $100,000, accounts receivable as 8% of revenue, inventory as 10% of revenue, accounts payable as 12% of cost of goods sold, Year 0 (historical year) NET PP&E of $300,000, historical debt of $200,000, and historical shareholder's equity of $308,000. The model also accounts for the assumption of the company paying $0.00 in dividends. If the company chooses to pay dividends in the future, note that they will reduce the free cash flow available for debt repayment or cash accumulation.
A7: 3. Key Drivers
A8: The biggest key drivers that mostly affect the company's valuation would be revenue growth, operating margin, discount rate, and terminal growth rate. Higher revenue growth, operating margin, and terminal growth increase the valuation because they raise the company's expected free cash flow. The discount rate has a negative effect on the company's valuation. The higher the discount rate, the harsher the future cash flows would be discounted to present time, and future cash flows would be worth a lot less in present time.
A9: 4. Valuation Result
A10: Given the company's base assumptions that it would have a 10% discount rate and a 3% terminal growth rate, the enterprise value is $1,808,953.12. This is a reasonable valuation because as mentioned earlier, the model uses discounted cash flow analysis to evaluate the company. This is where the company's projected cash flow for the 5-year period and the present value of its terminal value (which would keep growing in perpetuity beyond the forecasted period) are added together to achieve the enterprise value.
A11: 5. Limitations
A12: While the model covers a lot about the hypothetical company's 5-year forecast and potential changes in these projections if there is a change in terminal growth rate and discount rate (in the sensitivity analysis), there are still limitations present that the model doesn't cover. For example, this model is a simplified version. It doesn't go into depth on certain details, like equity for the balance sheet, or cash flow from investments or financing. Also, the model does not cover every real-world business risk. Mostly, it only covers the company's potential valuation if certain metrics (such as the discount rate and the growth rate) differ from expectations. The biggest thing to take note of from this entire model is that it is solely based on assumptions. That is the biggest limitation of the entire model.

Sheet Assumptions
A1: Hypothetical Company's Model Assumptions
A3: Revenue Assumptions
A4: Starting Revenue | B4: 1000000
A5: Revenue Growth Rate for each forecast year | B5: 0.05 | I5: Hypothetical Company's Sensitivity Analysis
A7: Expense Assumptions | I7: 2-Way Sensitivity Analysis | J7: Terminal Growth Rate
A8: Cost of goods sold as a percentage of revenue | B8: 0.6 | I8: ='DCF Valuation'!$B$11 -> 1808953.1 | J8: 0.01 | K8: 0.02 | L8: 0.03 | M8: 0.04 | N8: 0.05
A9: Operating expenses as a percentage of revenue | B9: 0.2 | I9: 0.08 | J9: 1934468.1 | K9: 2186176 | L9: 2538567 | M9: 3067153.6 | N9: 3948131.2
A10: Depreciation as a percentage of revenue or as a fixed amount | B10: 40000 | I10: 0.09 | J10: 1688368 | K10: 1870315.9 | L10: 2112913.2 | M10: 2452549.3 | N10: 2962003.5
A11: Tax Rate | B11: 0.25 | I11: 0.1 | J11: 1497093 | K11: 1633531.8 | L11: 1808953.1 | M11: 2042848.2 | N11: 2370301.3
I12: 0.11 | J12: 1344189.9 | K12: 1449460.4 | L12: 1581048.5 | M12: 1750233.3 | N12: 1975813
A13: Balance Sheet Assumptions | I13: 0.12 | J13: 1219188.8 | K13: 1302284 | L13: 1403844.9 | M13: 1530796.1 | N13: 1694018.9
A14: Cash | B14: 100000
A15: Accounts receivable as a percentage of revenue | B15: 0.08
A16: Inventory as a percentage of revenue | B16: 0.1
A17: Accounts payable as a percentage of cost of goods sold or revenue | B17: 0.12
A18: Capital expenditures as a percentage of revenue | B18: 0.04
A19: Dividends | B19: 0
A21: Historical Year Balance Sheet Assumptions
A22: Historical Net PP&E | B22: 300000
A23: Historical Debt | B23: 200000
A24: Historical Shareholder's Equity | B24: 308000
A26: DCF Assumptions
A27: Discount Rate | B27: 0.1
A28: Terminal Growth Rate | B28: 0.03

Sheet Income Statement
A1: Hypothetical Company's Pro-Forma Income Statement
A2: Income Statement | B2: Historical Year | C2: Year 1 | D2: Year 2 | E2: Year 3 | F2: Year 4 | G2: Year 5
A3: Revenue | B3: =Assumptions!B4 -> 1000000 | C3: =B3*(1+Assumptions!$B$5) -> 1050000 | D3: =C3*(1+Assumptions!$B$5) -> 1102500 | E3: =D3*(1+Assumptions!$B$5) -> 1157625 | F3: =E3*(1+Assumptions!$B$5) -> 1215506.2 | G3: =F3*(1+Assumptions!$B$5) -> 1276281.6
A4: Cost of Goods Sold | B4: =B3*Assumptions!$B$8 -> 600000 | C4: =C3*Assumptions!$B$8 -> 630000 | D4: =D3*Assumptions!$B$8 -> 661500 | E4: =E3*Assumptions!$B$8 -> 694575 | F4: =F3*Assumptions!$B$8 -> 729303.75 | G4: =G3*Assumptions!$B$8 -> 765768.94
A5: Gross Profit | B5: =B3-B4 -> 400000 | C5: =C3-C4 -> 420000 | D5: =D3-D4 -> 441000 | E5: =E3-E4 -> 463050 | F5: =F3-F4 -> 486202.5 | G5: =G3-G4 -> 510512.62
A7: Operating Expenses | B7: =B3*Assumptions!$B$9 -> 200000 | C7: =C3*Assumptions!$B$9 -> 210000 | D7: =D3*Assumptions!$B$9 -> 220500 | E7: =E3*Assumptions!$B$9 -> 231525 | F7: =F3*Assumptions!$B$9 -> 243101.25 | G7: =G3*Assumptions!$B$9 -> 255256.31
A8: EBITDA | B8: =B5-B7 -> 200000 | C8: =C5-C7 -> 210000 | D8: =D5-D7 -> 220500 | E8: =E5-E7 -> 231525 | F8: =F5-F7 -> 243101.25 | G8: =G5-G7 -> 255256.31
A9: Depreciation | B9: =Assumptions!$B$10 -> 40000 | C9: =Assumptions!$B$10 -> 40000 | D9: =Assumptions!$B$10 -> 40000 | E9: =Assumptions!$B$10 -> 40000 | F9: =Assumptions!$B$10 -> 40000 | G9: =Assumptions!$B$10 -> 40000
A10: EBIT | B10: =B8-B9 -> 160000 | C10: =C8-C9 -> 170000 | D10: =D8-D9 -> 180500 | E10: =E8-E9 -> 191525 | F10: =F8-F9 -> 203101.25 | G10: =G8-G9 -> 215256.31
A12: Taxes | B12: =B10*Assumptions!B11 -> 40000 | C12: =C10*Assumptions!$B$11 -> 42500 | D12: =D10*Assumptions!$B$11 -> 45125 | E12: =E10*Assumptions!$B$11 -> 47881.25 | F12: =F10*Assumptions!$B$11 -> 50775.312 | G12: =G10*Assumptions!$B$11 -> 53814.078
A13: Net Income | B13: =B10-B12 -> 120000 | C13: =C10-C12 -> 127500 | D13: =D10-D12 -> 135375 | E13: =E10-E12 -> 143643.75 | F13: =F10-F12 -> 152325.94 | G13: =G10-G12 -> 161442.23

Sheet Balance Sheet
A1: Hypothetical Company's Pro-Forma Balance Sheet
A2: Balance Sheet | B2: Historical Year | C2: Year 1 | D2: Year 2 | E2: Year 3 | F2: Year 4 | G2: Year 5
A3: Cash | B3: =Assumptions!$B$14 -> 100000 | C3: =B3+MAX(0,'Cash Flow Statement'!B11-Assumptions!$B$19-B11) -> 100000 | D3: =C3+MAX(0,'Cash Flow Statement'!C11-Assumptions!$B$19-C11) -> 145705 | E3: =D3+MAX(0,'Cash Flow Statement'!D11-Assumptions!$B$19-D11) -> 277090.25 | F3: =E3+MAX(0,'Cash Flow Statement'!E11-Assumptions!$B$19-E11) -> 414544.76 | G3: =F3+MAX(0,'Cash Flow Statement'!F11-Assumptions!$B$19-F11) -> 558372
A4: Accounts Receivable | B4: ='Income Statement'!B3*Assumptions!B$15 -> 80000 | C4: ='Income Statement'!C3*Assumptions!$B$15 -> 84000 | D4: ='Income Statement'!D3*Assumptions!$B$15 -> 88200 | E4: ='Income Statement'!E3*Assumptions!$B$15 -> 92610 | F4: ='Income Statement'!F3*Assumptions!$B$15 -> 97240.5 | G4: ='Income Statement'!G3*Assumptions!$B$15 -> 102102.53
A5: Inventory | B5: ='Income Statement'!B3*Assumptions!$B$16 -> 100000 | C5: ='Income Statement'!C3*Assumptions!$B$16 -> 105000 | D5: ='Income Statement'!D3*Assumptions!$B$16 -> 110250 | E5: ='Income Statement'!E3*Assumptions!$B$16 -> 115762.5 | F5: ='Income Statement'!F3*Assumptions!$B$16 -> 121550.62 | G5: ='Income Statement'!G3*Assumptions!$B$16 -> 127628.16
A6: Total Current Assets | B6: =SUM(B3:B5) -> 280000 | C6: =SUM(C3:C5) -> 289000 | D6: =SUM(D3:D5) -> 344155 | E6: =SUM(E3:E5) -> 485462.75 | F6: =SUM(F3:F5) -> 633335.89 | G6: =SUM(G3:G5) -> 788102.68
A7: Net Property, Plant & Equipment | B7: =Assumptions!B22 -> 300000 | C7: =B7+('Income Statement'!C3*Assumptions!$B$18)-'Income Statement'!C9 -> 302000 | D7: =C7+('Income Statement'!D3*Assumptions!$B$18)-'Income Statement'!D9 -> 306100 | E7: =D7+('Income Statement'!E3*Assumptions!$B$18)-'Income Statement'!E9 -> 312405 | F7: =E7+('Income Statement'!F3*Assumptions!$B$18)-'Income Statement'!F9 -> 321025.25 | G7: =F7+('Income Statement'!G3*Assumptions!$B$18)-'Income Statement'!G9 -> 332076.51
A8: Total Assets | B8: =B6+B7 -> 580000 | C8: =C6+C7 -> 591000 | D8: =D6+D7 -> 650255 | E8: =E6+E7 -> 797867.75 | F8: =F6+F7 -> 954361.14 | G8: =G6+G7 -> 1120179.2
A10: Accounts Payable | B10: ='Income Statement'!B4*Assumptions!$B$17 -> 72000 | C10: ='Income Statement'!C4*Assumptions!$B$17 -> 75600 | D10: ='Income Statement'!D4*Assumptions!$B$17 -> 79380 | E10: ='Income Statement'!E4*Assumptions!$B$17 -> 83349 | F10: ='Income Statement'!F4*Assumptions!$B$17 -> 87516.45 | G10: ='Income Statement'!G4*Assumptions!$B$17 -> 91892.272
A11: Debt | B11: =Assumptions!B23 -> 200000 | C11: =MAX(0,B11-('Cash Flow Statement'!B11-Assumptions!$B$19)) -> 79900 | D11: =MAX(0,C11-('Cash Flow Statement'!C11-Assumptions!$B$19)) -> 0 | E11: =MAX(0,D11-('Cash Flow Statement'!D11-Assumptions!$B$19)) -> 0 | F11: =MAX(0,E11-('Cash Flow Statement'!E11-Assumptions!$B$19)) -> 0 | G11: =MAX(0,F11-('Cash Flow Statement'!F11-Assumptions!$B$19)) -> 0
A12: Total Liabilities | B12: =B10+B11 -> 272000 | C12: =C10+C11 -> 155500 | D12: =D10+D11 -> 79380 | E12: =E10+E11 -> 83349 | F12: =F10+F11 -> 87516.45 | G12: =G10+G11 -> 91892.272
A13: Shareholder's Equity | B13: =Assumptions!$B$24 -> 308000 | C13: =B13+('Income Statement'!C13-Assumptions!$B$19) -> 435500 | D13: =C13+('Income Statement'!D13-Assumptions!$B$19) -> 570875 | E13: =D13+('Income Statement'!E13-Assumptions!$B$19) -> 714518.75 | F13: =E13+('Income Statement'!F13-Assumptions!$B$19) -> 866844.69 | G13: =F13+('Income Statement'!G13-Assumptions!$B$19) -> 1028286.9
A14: Total Liabilities & Equity | B14: =B12+B13 -> 580000 | C14: =C12+C13 -> 591000 | D14: =D12+D13 -> 650255 | E14: =E12+E13 -> 797867.75 | F14: =F12+F13 -> 954361.14 | G14: =G12+G13 -> 1120179.2

Sheet Cash Flow Statement
A1: Hypothetical Company's Pro-Forma Cash Flow Statement
A2: Cash Flow Statement | B2: Year 1 | C2: Year 2 | D2: Year 3 | E2: Year 4 | F2: Year 5
A3: Net Income | B3: ='Income Statement'!C13 -> 127500 | C3: ='Income Statement'!D13 -> 135375 | D3: ='Income Statement'!E13 -> 143643.75 | E3: ='Income Statement'!F13 -> 152325.94 | F3: ='Income Statement'!G13 -> 161442.23
A4: Depreciation | B4: ='Income Statement'!C9 -> 40000 | C4: ='Income Statement'!D9 -> 40000 | D4: ='Income Statement'!E9 -> 40000 | E4: ='Income Statement'!F9 -> 40000 | F4: ='Income Statement'!G9 -> 40000
A5: Change in Accounts Receivable | B5: ='Balance Sheet'!C4-'Balance Sheet'!B4 -> 4000 | C5: ='Balance Sheet'!D4-'Balance Sheet'!C4 -> 4200 | D5: ='Balance Sheet'!E4-'Balance Sheet'!D4 -> 4410 | E5: ='Balance Sheet'!F4-'Balance Sheet'!E4 -> 4630.5 | F5: ='Balance Sheet'!G4-'Balance Sheet'!F4 -> 4862.025
A6: Change in Inventory | B6: ='Balance Sheet'!C5-'Balance Sheet'!B5 -> 5000 | C6: ='Balance Sheet'!D5-'Balance Sheet'!C5 -> 5250 | D6: ='Balance Sheet'!E5-'Balance Sheet'!D5 -> 5512.5 | E6: ='Balance Sheet'!F5-'Balance Sheet'!E5 -> 5788.125 | F6: ='Balance Sheet'!G5-'Balance Sheet'!F5 -> 6077.5312
A7: Change in Accounts Payable | B7: ='Balance Sheet'!C10-'Balance Sheet'!B10 -> 3600 | C7: ='Balance Sheet'!D10-'Balance Sheet'!C10 -> 3780 | D7: ='Balance Sheet'!E10-'Balance Sheet'!D10 -> 3969 | E7: ='Balance Sheet'!F10-'Balance Sheet'!E10 -> 4167.45 | F7: ='Balance Sheet'!G10-'Balance Sheet'!F10 -> 4375.8225
A8: Cash Flow From Operations | B8: =B3+B4-B5-B6+B7 -> 162100 | C8: =C3+C4-C5-C6+C7 -> 169705 | D8: =D3+D4-D5-D6+D7 -> 177690.25 | E8: =E3+E4-E5-E6+E7 -> 186074.76 | F8: =F3+F4-F5-F6+F7 -> 194878.5
A10: Capital Expenditures | B10: ='Income Statement'!C3*Assumptions!$B$18 -> 42000 | C10: ='Income Statement'!D3*Assumptions!$B$18 -> 44100 | D10: ='Income Statement'!E3*Assumptions!$B$18 -> 46305 | E10: ='Income Statement'!F3*Assumptions!$B$18 -> 48620.25 | F10: ='Income Statement'!G3*Assumptions!$B$18 -> 51051.263
A11: Free Cash Flow | B11: =B8-B10 -> 120100 | C11: =C8-C10 -> 125605 | D11: =D8-D10 -> 131385.25 | E11: =E8-E10 -> 137454.51 | F11: =F8-F10 -> 143827.24

Sheet Free Cash Flow
A1: Hypothetical Company's Free Cash Flow
A2: Free Cash Flow | B2: Year 1 | C2: Year 2 | D2: Year 3 | E2: Year 4 | F2: Year 5
A3: EBIT | B3: ='Income Statement'!C10 -> 170000 | C3: ='Income Statement'!D10 -> 180500 | D3: ='Income Statement'!E10 -> 191525 | E3: ='Income Statement'!F10 -> 203101.25 | F3: ='Income Statement'!G10 -> 215256.31
A4: Taxes on EBIT | B4: =B3*Assumptions!$B$11 -> 42500 | C4: =C3*Assumptions!$B$11 -> 45125 | D4: =D3*Assumptions!$B$11 -> 47881.25 | E4: =E3*Assumptions!$B$11 -> 50775.312 | F4: =F3*Assumptions!$B$11 -> 53814.078
A5: NOPAT | B5: =B3-B4 -> 127500 | C5: =C3-C4 -> 135375 | D5: =D3-D4 -> 143643.75 | E5: =E3-E4 -> 152325.94 | F5: =F3-F4 -> 161442.23
A7: Depreciation | B7: ='Income Statement'!C9 -> 40000 | C7: ='Income Statement'!D9 -> 40000 | D7: ='Income Statement'!E9 -> 40000 | E7: ='Income Statement'!F9 -> 40000 | F7: ='Income Statement'!G9 -> 40000
A8: Capital Expenditures | B8: ='Cash Flow Statement'!B10 -> 42000 | C8: ='Cash Flow Statement'!C10 -> 44100 | D8: ='Cash Flow Statement'!D10 -> 46305 | E8: ='Cash Flow Statement'!E10 -> 48620.25 | F8: ='Cash Flow Statement'!F10 -> 51051.263
A9: Change in Net Working Capital | B9: ='Cash Flow Statement'!B5+'Cash Flow Statement'!B6-'Cash Flow Statement'!B7 -> 5400 | C9: ='Cash Flow Statement'!C5+'Cash Flow Statement'!C6-'Cash Flow Statement'!C7 -> 5670 | D9: ='Cash Flow Statement'!D5+'Cash Flow Statement'!D6-'Cash Flow Statement'!D7 -> 5953.5 | E9: ='Cash Flow Statement'!E5+'Cash Flow Statement'!E6-'Cash Flow Statement'!E7 -> 6251.175 | F9: ='Cash Flow Statement'!F5+'Cash Flow Statement'!F6-'Cash Flow Statement'!F7 -> 6563.7338
A10: Free Cash Flow | B10: =B5+B7-B8-B9 -> 120100 | C10: =C5+C7-C8-C9 -> 125605 | D10: =D5+D7-D8-D9 -> 131385.25 | E10: =E5+E7-E8-E9 -> 137454.51 | F10: =F5+F7-F8-F9 -> 143827.24

Sheet DCF Valuation
A1: Hypothetical Company's DCF Valuation
A2: DCF Valuation | B2: Year 1 | C2: Year 2 | D2: Year 3 | E2: Year 4 | F2: Year 5
A3: Free Cash Flow | B3: ='Free Cash Flow'!B10 -> 120100 | C3: ='Free Cash Flow'!C10 -> 125605 | D3: ='Free Cash Flow'!D10 -> 131385.25 | E3: ='Free Cash Flow'!E10 -> 137454.51 | F3: ='Free Cash Flow'!F10 -> 143827.24
A4: Discount Period | B4: 1 | C4: 2 | D4: 3 | E4: 4 | F4: 5
A5: Discount Factor | B5: =1/(1+Assumptions!$B$27)^B4 -> 0.90909091 | C5: =1/(1+Assumptions!$B$27)^C4 -> 0.82644628 | D5: =1/(1+Assumptions!$B$27)^D4 -> 0.7513148 | E5: =1/(1+Assumptions!$B$27)^E4 -> 0.68301346 | F5: =1/(1+Assumptions!$B$27)^F4 -> 0.62092132
A6: Present Value of Free Cash Flow | B6: =B3*B5 -> 109181.82 | C6: =C3*C5 -> 103805.79 | D6: =D3*D5 -> 98711.683 | E6: =E3*E5 -> 93883.282 | F6: =F3*F5 -> 89305.399
A8: Terminal Value | F8: =F3*((1+Assumptions!$B$28)/(Assumptions!$B$27-Assumptions!$B$28)) -> 2116315.1
A9: Present Value of Terminal Value | F9: =F8/(1+Assumptions!$B$27)^F4 -> 1314065.2
A11: Enterprise Value | B11: =SUM(B6:F6)+F9 -> 1808953.1

Sheet Sensitivity Analysis
A1: Hypothetical Company's Sensitivity Analysis (Linked from Assumptions)
A3: 2-Way Sensitivity Analysis | B3: Terminal Growth Rate
A4: ='DCF Valuation'!$B$11 -> 1808953.1 | B4: 0.01 | C4: 0.02 | D4: 0.03 | E4: 0.04 | F4: 0.05
A5: 0.08 | B5: =Assumptions!J9 -> 1934468.1 | C5: =Assumptions!K9 -> 2186176 | D5: =Assumptions!L9 -> 2538567 | E5: =Assumptions!M9 -> 3067153.6 | F5: =Assumptions!N9 -> 3948131.2
A6: 0.09 | B6: =Assumptions!J10 -> 1688368 | C6: =Assumptions!K10 -> 1870315.9 | D6: =Assumptions!L10 -> 2112913.2 | E6: =Assumptions!M10 -> 2452549.3 | F6: =Assumptions!N10 -> 2962003.5
A7: 0.1 | B7: =Assumptions!J11 -> 1497093 | C7: =Assumptions!K11 -> 1633531.8 | D7: =Assumptions!L11 -> 1808953.1 | E7: =Assumptions!M11 -> 2042848.2 | F7: =Assumptions!N11 -> 2370301.3
A8: 0.11 | B8: =Assumptions!J12 -> 1344189.9 | C8: =Assumptions!K12 -> 1449460.4 | D8: =Assumptions!L12 -> 1581048.5 | E8: =Assumptions!M12 -> 1750233.3 | F8: =Assumptions!N12 -> 1975813
A9: 0.12 | B9: =Assumptions!J13 -> 1219188.8 | C9: =Assumptions!K13 -> 1302284 | D9: =Assumptions!L13 -> 1403844.9 | E9: =Assumptions!M13 -> 1530796.1 | F9: =Assumptions!N13 -> 1694018.9
